PULSEY/PULSEY.py
PULSEY/__init__.py
pulsey-0.0.7.dist-info/METADATA
pulsey-0.0.7.dist-info/WHEEL
pulsey-0.0.7.dist-info/top_level.txt
pulsey-0.0.7.dist-info/RECORD
